superposedpulses/__init__.py
superposedpulses/example.py
superposedpulses/forcing.py
superposedpulses/point_model.py
superposedpulses/pulse_shape.py
superposedpulses/two_point_forcing.py
superposed_pulses-1.5.dist-info/LICENSE
superposed_pulses-1.5.dist-info/METADATA
superposed_pulses-1.5.dist-info/WHEEL
superposed_pulses-1.5.dist-info/top_level.txt
superposed_pulses-1.5.dist-info/RECORD
