Metadata-Version: 2.1
Name: superposed-pulses
Version: 1.5
Summary: Python scripts used by the fusion energy group at UiT The Arctic University of Norway.
Home-page: https://github.com/uit-cosmo/filtered-point-process
Download-URL: https://github.com/uit-cosmo/3ppy/archive/refs/tags/1.1.tar.gz
Author: Juan Manuel Losada
Author-email: juan.m.losada@uit.no
License: MiT
Classifier: Intended Audience :: Education
Classifier: Intended Audience :: Science/Research
Classifier: License :: OSI Approved :: MIT License
Classifier: Programming Language :: Python :: 3 :: Only
Classifier: Topic :: Scientific/Engineering :: Visualization
Requires-Python: >=3.0
License-File: LICENSE
Requires-Dist: numpy >=1.15.0
Requires-Dist: scipy >=1.4.0
Requires-Dist: tqdm >=4.50.2
